crackerjack/README.md
crackerjack/__init__.py
crackerjack/__main__.py
crackerjack/api.py
crackerjack/ci_feedback.py
crackerjack/code_cleaner.py
crackerjack/errors.py
crackerjack/interactive.py
crackerjack/py313.py
crackerjack/reflection_loop.py
crackerjack/server.py
crackerjack/adapters/README.md
crackerjack/adapters/__init__.py
crackerjack/adapters/_output_paths.py
crackerjack/adapters/_qa_adapter_base.py
crackerjack/adapters/_tool_adapter_base.py
crackerjack/adapters/ai/README.md
crackerjack/adapters/ai/__init__.py
crackerjack/adapters/ai/base.py
crackerjack/adapters/ai/claude.py
crackerjack/adapters/ai/ollama.py
crackerjack/adapters/ai/qwen.py
crackerjack/adapters/ai/registry.py
crackerjack/adapters/complexity/README.md
crackerjack/adapters/complexity/__init__.py
crackerjack/adapters/complexity/complexipy.py
crackerjack/adapters/dependency/__init__.py
crackerjack/adapters/dependency/pip_audit.py
crackerjack/adapters/format/README.md
crackerjack/adapters/format/__init__.py
crackerjack/adapters/format/mdformat.py
crackerjack/adapters/format/ruff.py
crackerjack/adapters/lint/README.md
crackerjack/adapters/lint/__init__.py
crackerjack/adapters/lint/codespell.py
crackerjack/adapters/lsp/README.md
crackerjack/adapters/lsp/__init__.py
crackerjack/adapters/lsp/_base.py
crackerjack/adapters/lsp/_client.py
crackerjack/adapters/lsp/_manager.py
crackerjack/adapters/lsp/skylos.py
crackerjack/adapters/lsp/zuban.py
crackerjack/adapters/refactor/README.md
crackerjack/adapters/refactor/__init__.py
crackerjack/adapters/refactor/creosote.py
crackerjack/adapters/refactor/refurb.py
crackerjack/adapters/refactor/skylos.py
crackerjack/adapters/sast/README.md
crackerjack/adapters/sast/__init__.py
crackerjack/adapters/sast/_base.py
crackerjack/adapters/sast/bandit.py
crackerjack/adapters/sast/pyscn.py
crackerjack/adapters/sast/semgrep.py
crackerjack/adapters/security/README.md
crackerjack/adapters/security/__init__.py
crackerjack/adapters/security/gitleaks.py
crackerjack-0.50.6.dist-info/METADATA
crackerjack-0.50.6.dist-info/WHEEL
crackerjack-0.50.6.dist-info/entry_points.txt
crackerjack-0.50.6.dist-info/licenses/LICENSE
crackerjack-0.50.6.dist-info/RECORD
