Metadata-Version: 2.4
Name: crackerjack
Version: 0.50.6
Summary: Crackerjack Python project management tool
Project-URL: documentation, https://github.com/lesleslie/crackerjack
Project-URL: homepage, https://github.com/lesleslie/crackerjack
Project-URL: repository, https://github.com/lesleslie/crackerjack
Author-email: Les Leslie <les@wedgwoodwebworks.com>
License: BSD-3-CLAUSE
License-File: LICENSE
Classifier: Operating System :: POSIX
Classifier: Programming Language :: Python
Classifier: Programming Language :: Python :: 3 :: Only
Classifier: Programming Language :: Python :: 3.13
Classifier: Topic :: Software Development :: Libraries :: Python Modules
Classifier: Topic :: Software Development :: Quality Assurance
Classifier: Topic :: Software Development :: Testing
Classifier: Topic :: Utilities
Classifier: Typing :: Typed
Requires-Python: >=3.13
Requires-Dist: aiofiles>=25.1.0
Requires-Dist: aiohttp>=3.13.2
Requires-Dist: bandit>=1.9.2
Requires-Dist: codespell>=2.4.1
Requires-Dist: complexipy>=5.1.0
Requires-Dist: creosote>=4.1.0
Requires-Dist: fastapi>=0.124.2
Requires-Dist: fastmcp>=2.13.2
Requires-Dist: hatchling>=1.28.0
Requires-Dist: hypothesis>=6.148.7
Requires-Dist: keyring>=25.7.0
Requires-Dist: linkcheckmd>=1.4.0
Requires-Dist: mcp-common>=0.3.6
Requires-Dist: mcp>=1.23.3
Requires-Dist: mdformat-ruff>=0.1.3
Requires-Dist: mdformat>=1.0.0
Requires-Dist: nltk>=3.9.2
Requires-Dist: numpy>=2.3.5
Requires-Dist: oneiric>=0.3.2
Requires-Dist: onnxruntime>=1.23.2
Requires-Dist: pip-audit>=2.10.0
Requires-Dist: psutil>=7.1.3
Requires-Dist: pydantic>=2.12.5
Requires-Dist: pyleak>=0.1.14
Requires-Dist: pyright>=1.1.407
Requires-Dist: pyscn==1.5.0
Requires-Dist: pytest-asyncio>=1.3.0
Requires-Dist: pytest-benchmark>=5.2.3
Requires-Dist: pytest-cov>=7.0.0
Requires-Dist: pytest-mock>=3.15.1
Requires-Dist: pytest-timeout>=2.4.0
Requires-Dist: pytest-xdist>=3.8.0
Requires-Dist: pytest>=9.0.2
Requires-Dist: pyyaml>=6.0.3
Requires-Dist: refurb>=2.2.0
Requires-Dist: rich>=14.2.0
Requires-Dist: ruff>=0.14.8
Requires-Dist: scikit-learn>=1.8.0
Requires-Dist: scipy-stubs>=1.16.3.3
Requires-Dist: scipy>=1.16.3
Requires-Dist: skylos>=2.5.3
Requires-Dist: structlog>=25.5.0
Requires-Dist: tomli-w>=1.2.0
Requires-Dist: transformers>=4.57.3
Requires-Dist: typer>=0.20.0
Requires-Dist: types-aiofiles>=25.1.0.20251011
Requires-Dist: types-psutil>=7.1.3.20251211
Requires-Dist: types-pyyaml>=6.0.12.20250915
Requires-Dist: uv-bump>=0.3.2
Requires-Dist: uv>=0.9.17
Requires-Dist: uvicorn>=0.38.0
Requires-Dist: vulture>=2.14
Requires-Dist: watchdog>=6.0.0
Requires-Dist: websockets>=15.0.1
Requires-Dist: zuban>=0.3.0
